COPYING
MANIFEST.in
README.md
setup.py
valkka/discovery/__init__.py
valkka/discovery/arp.py
valkka/discovery/base.py
valkka/discovery/datatype.py
valkka/discovery/ipconfig.py
valkka/discovery/probe.py
valkka/discovery/version.py
valkka/discovery/camsearch/__init__.py
valkka/discovery/camsearch/base.py
valkka/discovery/camsearch/cli.py
valkka/discovery/camsearch/cli_old.py
valkka/discovery/camsearch/datatype.py
valkka/discovery/wsdiscovery/__init__.py
valkka/discovery/wsdiscovery/cmdline.py
valkka/discovery/wsdiscovery/daemon.py
valkka/discovery/wsdiscovery/envelope.py
valkka/discovery/wsdiscovery/message.py
valkka/discovery/wsdiscovery/namespaces.py
valkka/discovery/wsdiscovery/qname.py
valkka/discovery/wsdiscovery/scope.py
valkka/discovery/wsdiscovery/service.py
valkka/discovery/wsdiscovery/udp.py
valkka/discovery/wsdiscovery/uri.py
valkka/discovery/wsdiscovery/util.py
valkka/discovery/wsdiscovery/actions/__init__.py
valkka/discovery/wsdiscovery/actions/bye.py
valkka/discovery/wsdiscovery/actions/hello.py
valkka/discovery/wsdiscovery/actions/probe.py
valkka/discovery/wsdiscovery/actions/probematch.py
valkka/discovery/wsdiscovery/actions/resolve.py
valkka/discovery/wsdiscovery/actions/resolvematch.py
valkka/onvif/__init__.py
valkka/onvif/base.py
valkka/onvif/version.py
valkka/onvif/multiprocess/__init__.py
valkka/onvif/multiprocess/base.py
valkka/onvif/wsdl/accesscontrol-10.wsdl
valkka/onvif/wsdl/accessrules-10.wsdl
valkka/onvif/wsdl/actionengine-10.wsdl
valkka/onvif/wsdl/advancedsecurity-10.wsdl
valkka/onvif/wsdl/analytics-20.wsdl
valkka/onvif/wsdl/appmgmt-10.wsdl
valkka/onvif/wsdl/authenticationbehavior-10.wsdl
valkka/onvif/wsdl/b-2.xsd
valkka/onvif/wsdl/bf-2.xsd
valkka/onvif/wsdl/common-10.xsd
valkka/onvif/wsdl/common.xsd
valkka/onvif/wsdl/credential-10.wsdl
valkka/onvif/wsdl/deviceio-10.wsdl
valkka/onvif/wsdl/devicemgmt-10.wsdl
valkka/onvif/wsdl/display-10.wsdl
valkka/onvif/wsdl/doorcontrol-10.wsdl
valkka/onvif/wsdl/event-10.wsdl
valkka_onvif.egg-info/PKG-INFO
valkka_onvif.egg-info/SOURCES.txt
valkka_onvif.egg-info/dependency_links.txt
valkka_onvif.egg-info/entry_points.txt
valkka_onvif.egg-info/requires.txt
valkka_onvif.egg-info/top_level.txt