Metadata-Version: 2.1
Name: valkka-onvif
Version: 1.6.6
Summary: Onvif python dependencies for libValkka
Home-page: https://elsampsa.github.io/valkka-examples/_build/html/onvif.html
Author: Sampsa Riikonen
Author-email: sampsa.riikonen@iki.fi
License: MIT
Project-URL: Valkka library, https://elsampsa.github.io/valkka-examples/
Keywords: valkka video surveillance onvif
Platform: UNKNOWN
Classifier: Development Status :: 3 - Alpha
Classifier: Intended Audience :: Developers
Classifier: Operating System :: POSIX :: Linux
Classifier: Topic :: Multimedia :: Video
Classifier: License :: OSI Approved :: MIT License
Classifier: Programming Language :: Python :: 3
License-File: COPYING
